image_validator/__init__.py
image_validator/core.py
image_validator/face_detection.py
image_validator/image_quality_check.py
image_validator/text_extraction.py
image_validator-0.1.0.dist-info/METADATA
image_validator-0.1.0.dist-info/WHEEL
image_validator-0.1.0.dist-info/top_level.txt
image_validator-0.1.0.dist-info/RECORD
