Metadata-Version: 2.1
Name: image-validator
Version: 0.1.0
Summary: A package to detect fake or low-quality images using OpenCV and Tesseract
Author: Vinayak Gaikwad
Author-email: gaikwadvinayak1282@gmail.com
Classifier: Programming Language :: Python :: 3
Classifier: Operating System :: OS Independent
Requires-Python: >=3.6
Requires-Dist: Pillow
Requires-Dist: numpy
Requires-Dist: opencv-python
Requires-Dist: pytesseract
